pyqfm/__init__.py
pyqfm/pylibQFM_SDK.py
pyqfm/pyqfm.py
pyqfm/qfmtool.py
pyqfm/qfmui.py
pyqfm/uiprovider.py
pyqfm/lib/arm/release/libQFM_SDK.a
pyqfm/lib/arm/release/libQFM_SDK.so
pyqfm/lib/arm/release/libQFM_SDK.so.0
pyqfm/lib/arm/release/libQFM_SDK.so.0.6.0
pyqfm/lib/arm64/release/libQFM_SDK.a
pyqfm/lib/arm64/release/libQFM_SDK.so
pyqfm/lib/arm64/release/libQFM_SDK.so.0
pyqfm/lib/arm64/release/libQFM_SDK.so.0.5.12
pyqfm/lib/arm64/release/libQFM_SDK.so.0.6.0
pyqfm/lib/win-x64/QFM_SDK_DLL.dll
pyqfm/lib/win-x64/QFM_SDK_DLL.lib
pyqfm/lib/x86_64/release/libQFM_SDK.a
pyqfm/lib/x86_64/release/libQFM_SDK.so
pyqfm/lib/x86_64/release/libQFM_SDK.so.0
pyqfm/lib/x86_64/release/libQFM_SDK.so.0.6.0
pyqfm-0.6.0.dist-info/METADATA
pyqfm-0.6.0.dist-info/WHEEL
pyqfm-0.6.0.dist-info/entry_points.txt
pyqfm-0.6.0.dist-info/top_level.txt
pyqfm-0.6.0.dist-info/RECORD
