Metadata-Version: 2.1
Name: pyqfm
Version: 0.6.0
Summary: QFM SDK for Python
Home-page: https://suprema.ai/
Author-email: youngsukkim@suprema.co.kr
License: UNKNOWN
Platform: UNKNOWN
